avocado_ansible/module.py
avocado_framework_plugin_ansible-113.0.dist-info/METADATA
avocado_framework_plugin_ansible-113.0.dist-info/WHEEL
avocado_framework_plugin_ansible-113.0.dist-info/entry_points.txt
avocado_framework_plugin_ansible-113.0.dist-info/top_level.txt
avocado_framework_plugin_ansible-113.0.dist-info/RECORD
