Metadata-Version: 2.4
Name: avocado-framework-plugin-ansible
Version: 113.0
Summary: Adds to Avocado the ability to use ansible modules as dependencies for tests
Home-page: http://avocado-framework.github.io/
Author: Avocado Developers
Author-email: avocado-devel@redhat.com
Requires-Dist: avocado-framework==113.0
Requires-Dist: cffi==1.17.1; python_version < "3.10"
Requires-Dist: cffi; python_version >= "3.10"
Requires-Dist: cryptography<46.0.0; python_version < "3.10"
Requires-Dist: pycparser
Requires-Dist: ansible-core
Requires-Dist: markupsafe<3.0.0
Dynamic: author
Dynamic: author-email
Dynamic: description
Dynamic: description-content-type
Dynamic: home-page
Dynamic: requires-dist
Dynamic: summary
